7d9aa9f3dd924899ed09__mypyc.cpython-37m-x86_64-linux-gnu.so
parsing/automaton.py
parsing/interfaces.py
parsing/glrparser.py
parsing/_version.py
parsing/lrparser.py
parsing/grammar.cpython-37m-x86_64-linux-gnu.so
parsing/__init__.py
parsing/py.typed
parsing/module_spec.py
parsing/automaton.cpython-37m-x86_64-linux-gnu.so
parsing/introspection.py
parsing/ast.py
parsing/errors.py
parsing/grammar.py
parsing/tests/test_codestyle.py
parsing/tests/__main__.py
parsing/tests/__init__.py
parsing/tests/test_basic.py
parsing/tests/specs/b.py
parsing/tests/specs/h.py
parsing/tests/specs/i.py
parsing/tests/specs/a.py
parsing/tests/specs/__init__.py
parsing/tests/specs/d.py
parsing-2.0.4.dist-info/LICENSE
parsing-2.0.4.dist-info/METADATA
parsing-2.0.4.dist-info/RECORD
parsing-2.0.4.dist-info/top_level.txt
parsing-2.0.4.dist-info/WHEEL
