Metadata-Version: 2.1
Name: parsing
Version: 2.0.4
Summary: LR(1) parser generator for Python and CFSM and GLR parser drivers
Author-email: Jason Evans <jasone@canonware.com>
License: Copyright (c) 2007 Jason Evans <jasone@canonware.com>
Classifier: Development Status :: 5 - Production/Stable
Classifier: Intended Audience :: Developers
Classifier: License :: OSI Approved :: MIT License
Classifier: Operating System :: OS Independent
Classifier: Programming Language :: Python :: 3
Classifier: Topic :: Software Development :: Compilers
Classifier: Topic :: Text Processing :: General
Requires-Python: >=3.7.0
License-File: LICENSE
Requires-Dist: mypy-extensions>=1.0.0
Provides-Extra: test
Requires-Dist: flake8; extra == "test"
Requires-Dist: mypy>=1.4.1; extra == "test"
